reddit_user_to_sqlite/__init__.py
reddit_user_to_sqlite/cli.py
reddit_user_to_sqlite/csv_helpers.py
reddit_user_to_sqlite/helpers.py
reddit_user_to_sqlite/reddit_api.py
reddit_user_to_sqlite/sqlite_helpers.py
reddit_user_to_sqlite-0.4.2.dist-info/entry_points.txt
reddit_user_to_sqlite-0.4.2.dist-info/LICENSE
reddit_user_to_sqlite-0.4.2.dist-info/WHEEL
reddit_user_to_sqlite-0.4.2.dist-info/METADATA
reddit_user_to_sqlite-0.4.2.dist-info/RECORD
