Metadata-Version: 2.1
Name: reddit-user-to-sqlite
Version: 0.4.2
Summary: Create a SQLite database containing data pulled from Reddit about a single user.
Keywords: sqlite,reddit,dogsheep
Author-email: David Brownman <beamneocube@gmail.com>
Requires-Python: >=3.9
Classifier: Programming Language :: Python :: 3
Classifier: Development Status :: 3 - Alpha
Classifier: Environment :: Console
Classifier: License :: OSI Approved :: MIT License
Classifier: Operating System :: OS Independent
Classifier: Natural Language :: English
Requires-Dist: sqlite-utils==3.32.1
Requires-Dist: click==8.1.3
Requires-Dist: requests==2.29.0
Requires-Dist: tqdm==4.65.0
Requires-Dist: black==23.3.0 ; extra == "ci"
Requires-Dist: pyright==1.1.318 ; extra == "ci"
Requires-Dist: ruff==0.0.277 ; extra == "ci"
Requires-Dist: twine==4.0.2 ; extra == "release"
Requires-Dist: build==0.10.0 ; extra == "release"
Requires-Dist: pytest==7.3.1 ; extra == "test"
Requires-Dist: responses==0.23.1 ; extra == "test"
Project-URL: Author, https://xavd.id
Project-URL: Bug Tracker, https://github.com/xavdid/reddit-user-to-sqlite/issues
Project-URL: Changelog, https://github.com/xavdid/reddit-user-to-sqlite/blob/main/CHANGELOG.md
Project-URL: Homepage, https://github.com/xavdid/reddit-user-to-sqlite
Provides-Extra: ci
Provides-Extra: release
Provides-Extra: test
